{
  "lines":[
    {
      "tag":"Data",
      "isdata":true,
      "color":1,
      "fill":0,
      "marker":20,
      "label":"Data",
      "files":[
        {
          "tag":"Data_2016B",
          "xsec":1.0,
          "br":1.0,
          "recordedLumi":5788,
          "paths":[
            {
              "path":"/lstore/cms/cbeiraod/Stop4Body/GridProd/JetHT_Run2016B_03Feb2017_v2",
              "split":551
            }
          ]
        },
        {
          "tag":"Data_2016C",
          "xsec":1.0,
          "br":1.0,
          "recordedLumi":2573,
          "paths":[
            {
              "path":"/lstore/cms/cbeiraod/Stop4Body/GridProd/JetHT_Run2016C_03Feb2017",
              "split":414
            }
          ]
        },
        {
          "tag":"Data_2016D",
          "xsec":1.0,
          "br":1.0,
          "recordedLumi":4248,
          "paths":[
            {
              "path":"/lstore/cms/cbeiraod/Stop4Body/GridProd/JetHT_Run2016D_03Feb2017",
              "split":658
            }
          ]
        },
        {
          "tag":"Data_2016E",
          "xsec":1.0,
          "br":1.0,
          "recordedLumi":4009,
          "paths":[
            {
              "path":"/lstore/cms/cbeiraod/Stop4Body/GridProd/JetHT_Run2016E_03Feb2017",
              "split":669
            }
          ]
        },
        {
          "tag":"Data_2016F",
          "xsec":1.0,
          "br":1.0,
          "recordedLumi":3102,
          "paths":[
            {
              "path":"/lstore/cms/cbeiraod/Stop4Body/GridProd/JetHT_Run2016F_03Feb2017",
              "split":475
            }
          ]
        },
        {
          "tag":"Data_2016G",
          "xsec":1.0,
          "br":1.0,
          "recordedLumi":7539,
          "paths":[
            {
              "path":"/lstore/cms/cbeiraod/Stop4Body/GridProd/JetHT_Run2016G_03Feb2017",
              "split":593
            }
          ]
        },
        {
          "tag":"Data_2016H_v2",
          "xsec":1.0,
          "br":1.0,
          "recordedLumi":8391,
          "paths":[
            {
              "path":"/lstore/cms/cbeiraod/Stop4Body/GridProd/JetHT_Run2016H_03Feb2017_v2",
              "split":594
            }
          ]
        },
        {
          "tag":"Data_2016H_v3",
          "xsec":1.0,
          "br":1.0,
          "recordedLumi":215,
          "paths":[
            {
              "path":"/lstore/cms/cbeiraod/Stop4Body/GridProd/JetHT_Run2016H_03Feb2017_v3",
              "split":31
            }
          ]
        }
      ]
    }
  ]
}
