{
  "lines":[
    {
      "tag":"DYJets",
      "isdata":false,
      "color":831,
      "lcolor":1,
      "label":"DY + Jets",
      "files":[
        {
          "tag":"DYJetsToLL_M50_HT100to200",
          "xsec":1.0,
          "br":1.0,
          "paths":[
            {
              "path":"/lstore/cms/cbeiraod/Stop4Body/GridProd/DYJetsToLL_M50_HT100to200",
              "split":39
            },
            {
              "path":"/lstore/cms/cbeiraod/Stop4Body/GridProd/DYJetsToLL_M50_HT100to200_ext",
              "split":135
            }
          ]
        },
        {
          "tag":"DYJetsToLL_M50_HT200to400",
          "xsec":1.0,
          "br":1.0,
          "paths":[
            {
              "path":"/lstore/cms/cbeiraod/Stop4Body/GridProd/DYJetsToLL_M50_HT200to400",
              "split":40
            },
            {
              "path":"/lstore/cms/cbeiraod/Stop4Body/GridProd/DYJetsToLL_M50_HT200to400_ext",
              "split":130
            }
          ]
        },
        {
          "tag":"DYJetsToLL_M50_HT400to600",
          "xsec":1.0,
          "br":1.0,
          "paths":[
            {
              "path":"/lstore/cms/cbeiraod/Stop4Body/GridProd/DYJetsToLL_M50_HT400to600",
              "split":20
            },
            {
              "path":"/lstore/cms/cbeiraod/Stop4Body/GridProd/DYJetsToLL_M50_HT400to600_ext",
              "split":165
            }
          ]
        },
        {
          "tag":"DYJetsToLL_M50_HT600to800",
          "xsec":1.0,
          "br":1.0,
          "paths":[
            {
              "path":"/lstore/cms/cbeiraod/Stop4Body/GridProd/DYJetsToLL_M50_HT600to800",
              "split":176
            }
          ]
        },
        {
          "tag":"DYJetsToLL_M50_HT800to1200",
          "xsec":1.0,
          "br":1.0,
          "paths":[
            {
              "path":"/lstore/cms/cbeiraod/Stop4Body/GridProd/DYJetsToLL_M50_HT800to1200",
              "split":82
            }
          ]
        },
        {
          "tag":"DYJetsToLL_M50_HT1200to2500",
          "xsec":1.0,
          "br":1.0,
          "paths":[
            {
              "path":"/lstore/cms/cbeiraod/Stop4Body/GridProd/DYJetsToLL_M50_HT1200to2500",
              "split":33
            }
          ]
        },
        {
          "tag":"DYJetsToLL_M50_HT2500toInf",
          "xsec":1.0,
          "br":1.0,
          "paths":[
            {
              "path":"/lstore/cms/cbeiraod/Stop4Body/GridProd/DYJetsToLL_M50_HT2500toInf",
              "split":17
            }
          ]
        },
        {
          "tag":"DYJetsToLL_M5to50_HT100to200",
          "xsec":1.0,
          "br":1.0,
          "paths":[
            {
              "path":"/lstore/cms/cbeiraod/Stop4Body/GridProd/DYJetsToLL_M5to50_HT100to200",
              "split":13
            },
            {
              "path":"/lstore/cms/cbeiraod/Stop4Body/GridProd/DYJetsToLL_M5to50_HT100to200_ext",
              "split":91
            }
          ]
        },
        {
          "tag":"DYJetsToLL_M5to50_HT200to400",
          "xsec":1.0,
          "br":1.0,
          "paths":[
            {
              "path":"/lstore/cms/cbeiraod/Stop4Body/GridProd/DYJetsToLL_M5to50_HT200to400",
              "split":53
            },
            {
              "path":"/lstore/cms/cbeiraod/Stop4Body/GridProd/DYJetsToLL_M5to50_HT200to400_ext",
              "split":25
            }
          ]
        },
        {
          "tag":"DYJetsToLL_M5to50_HT400to600",
          "xsec":1.0,
          "br":1.0,
          "paths":[
            {
              "path":"/lstore/cms/cbeiraod/Stop4Body/GridProd/DYJetsToLL_M5to50_HT400to600",
              "split":19
            },
            {
              "path":"/lstore/cms/cbeiraod/Stop4Body/GridProd/DYJetsToLL_M5to50_HT400to600_ext",
              "split":35
            }
          ]
        },
        {
          "tag":"DYJetsToLL_M5to50_HT600toInf",
          "xsec":1.0,
          "br":1.0,
          "paths":[
            {
              "path":"/lstore/cms/cbeiraod/Stop4Body/GridProd/DYJetsToLL_M5to50_HT600toInf",
              "split":18
            },
            {
              "path":"/lstore/cms/cbeiraod/Stop4Body/GridProd/DYJetsToLL_M5to50_HT600toInf_ext",
              "split":48
            }
          ]
        }
      ]
    }
  ]
}
